<?xml version="1.0" encoding="UTF-8"?>
<!DOCTYPE generatorConfiguration PUBLIC "-//mybatis.org//DTD MyBatis Generator Configuration 1.0//EN" "http://mybatis.org/dtd/mybatis-generator-config_1_0.dtd">
<generatorConfiguration>

<!-- 	<classPathEntry -->
<!-- 		location="D:\work\gitaaa\web\src\main\resources\mysql-connector-java-5.1.45.jar" /> -->
		
	<classPathEntry
		location="D:\workspace3\web\src\main\resources\mysql-connector-java-5.1.45.jar" />
		
	<context id="context1">

		<commentGenerator>
			<property name="suppressDate" value="true" />
			<!-- 是否去除自动生成的注释 true：是 ： false:否 -->
			<property name="suppressAllComments" value="true" />
		</commentGenerator>

		<jdbcConnection
			connectionURL="jdbc:mysql://120.78.211.181:3306/xiangxing?useUnicode=true&amp;characterEncoding=utf-8&amp;autoReconnectForPools=true"
			driverClass="com.mysql.jdbc.Driver" password="123456" userId="root" />
		<javaModelGenerator targetPackage="com.xiangxing.model"
			targetProject="src/main/java" />
		<sqlMapGenerator targetPackage="com.xiangxing.mapper"
			targetProject="src/main/java" />
		<javaClientGenerator targetPackage="com.xiangxing.mapper"
			targetProject="src/main/java"
			type="XMLMAPPER" />

<!-- 		<table tableName="menu" domainObjectName="Menu"></table>-->
<!-- 		<table tableName="user" domainObjectName="User"></table> -->
<!-- 		<table tableName="user_menu" domainObjectName="UserMenu"></table> -->
<!-- 		<table tableName="t_advertising" domainObjectName="Advertising"></table> -->
<!-- 		<table tableName="t_course" domainObjectName="Course"></table> -->
<!-- 		<table tableName="t_entry_form" domainObjectName="EntryForm"></table> -->
<!-- 		<table tableName="t_exam" domainObjectName="Exam"></table> -->
<!-- 		<table tableName="t_school_image" domainObjectName="SchoolImage"></table> -->
<!-- 		<table tableName="t_order" domainObjectName="Order"></table> -->
<!-- 		<table tableName="t_product" domainObjectName="Product">
		<generatedKey column="id" sqlStatement="MySql" identity="true" />
		
		</table>  -->
<!-- 		<table tableName="t_school" domainObjectName="School"></table> -->
<!-- 		<table tableName="t_student" domainObjectName="Student"></table> -->
	<!-- 	<table tableName="t_exam_rank" domainObjectName="ExamRank"></table> -->
<!-- 		<table tableName="t_student_course" domainObjectName="StudentCourse"></table> -->
<!-- 		<table tableName="t_subject" domainObjectName="Subject"></table> -->
<!-- 		<table tableName="t_teacher" domainObjectName="Teacher"></table> -->
 <!-- <table tableName="t_homework" domainObjectName="Homework">
<generatedKey column="id" sqlStatement="MySql" identity="true" />
</table>  -->
<!-- <table tableName="t_student_homework" domainObjectName="StudentHomework">
<generatedKey column="id" sqlStatement="MySql" identity="true" />
</table>  -->

<!-- <table tableName="t_advert" domainObjectName="Advert">
		<generatedKey column="id" sqlStatement="MySql" identity="true" />
		
		</table>  -->
		<table tableName="t_version" domainObjectName="Version"></table> 
		
<!-- <table tableName="t_notice" domainObjectName="Notice">
<generatedKey column="id" sqlStatement="MySql" identity="true" /></table>  -->
<!--  <table tableName="t_notice_detail" domainObjectName="NoticeDetail"> -->
<!-- <generatedKey column="id" sqlStatement="MySql" identity="true" /></table>   -->

<!-- <table tableName="t_course_sign" domainObjectName="CourseSign"></table> -->
<!--  <table tableName="t_message" domainObjectName="Message">
<generatedKey column="id" sqlStatement="MySql" identity="true" /></table>   -->
<!--  <table tableName="t_contact" domainObjectName="Contact"> -->
<!-- <generatedKey column="id" sqlStatement="MySql" identity="true" /></table>  -->

<!--  <table tableName="t_message_queue" domainObjectName="MessageQueue">
<generatedKey column="id" sqlStatement="MySql" identity="true" /></table>   -->
		
	</context>
</generatorConfiguration>